{
    "Stocks": [
      {
        "stockID": "AMRN",
        "stockName": "Amarin Corporation plc",
        "qty": 1,
        "totalBalance": 7260.55,
        "history": {
            "ytd": {
                "Jan": 7494.38,
                "Feb": 7410.67,
                "Mar": 7388.32,
                "Apr": 7254.19,
                "May": 7260.55
            }
        }
      },
      {
        "stockID": "AKRO",
        "stockName": "Akero Therapeutics, Inc.",
        "qty": 1,
        "totalBalance": 3675.11,
        "history": {
            "ytd": {
                "Jan": 3595.83,
                "Feb": 3501.12,
                "Mar": 3576.23,
                "Apr": 3652.45,
                "May": 3675.11
            }
        }
      },
      {
        "stockID": "AAPL",
        "stockName": "Apple, Inc.",
        "qty": 2,
        "totalBalance": 1680.74,
        "history": {
            "ytd": {
                "Jan": 1857.01,
                "Feb": 1797.16,
                "Mar": 1704.98,
                "Apr": 1676.48,
                "May": 1680.74
            }
        }
      }, 
      {
        "AllStocks": {
            "ytd": {
                "Jan": 12947.22,
                "Feb": 13414.33,
                "Mar": 12788.74,
                "Apr": 12583.12,
                "May": 12616.40
            }
        }
      }
    ],
    "Bonds": [
      {
        "source": "The Bond Fund of America (Class F-2)",
        "period": "10yr",
        "amount": 12535.65,
        "history": {
            "ytd": {
                "Jan": 12154.22,
                "Feb": 12265.12,
                "Mar": 12311.54,
                "Apr": 12478.98,
                "May": 12535.65
            }
        }
      },
      {
        "source": "Morningstar Intermediate-Term Core Bond",
        "period": "10yr",
        "amount": 5722.22,
        "history": {
            "ytd": {
                "Jan": 5492.60,
                "Feb": 5550.32,
                "Mar": 5611.68,
                "Apr": 5692.97,
                "May": 5722.22
            }
        }
      },
      {
        "AllBonds": {
            "ytd": {
                "Jan": 17646.82,
                "Feb": 17815.44,
                "Mar": 17923.22,
                "Apr": 18171.95,
                "May": 18257.87
            }
        }
      }
    ],
    "Annuity": [
    ],
    "Mutual Funds": [
      {
        "stockID": "FTRNX",
        "stockName": "Fidelity Trend Fund",
        "qty": 1,
        "totalBalance": 7260.55,
        "history": {
            "ytd": {
                "Jan": 7494.38,
                "Feb": 7410.67,
                "Mar": 7388.32,
                "Apr": 7254.19,
                "May": 7260.55
            }
        }
      },
      {
        "stockID": "TRBCX",
        "stockName": "T. Rowe Price Blue Chip Growth Fund",
        "qty": 1,
        "totalBalance": 3675.11,
        "history": {
            "ytd": {
                "Jan": 3595.83,
                "Feb": 3501.12,
                "Mar": 3576.23,
                "Apr": 3652.45,
                "May": 3675.11
            }
        }
      }, 
      {
        "AllMutualFunds": {
            "ytd": {
                "Jan": 12947.22,
                "Feb": 13414.33,
                "Mar": 12788.74,
                "Apr": 12583.12,
                "May": 12616.40
            }
        }
      }
    ],
    "Cash": [
      {
        "source": "Money Market Savings",
        "amount": 56205.33,
        "history": {
            "ytd": {
                "Jan": 56221.13,
                "Feb": 56256.11,
                "Mar": 56235.85,
                "Apr": 56197.88,
                "May": 56205.33
            }
        }
      },
      {
        "source": "High Yield Savings",
        "amount": 9912.53,
        "history": {
            "ytd": {
                "Jan": 9811.37,
                "Feb": 9807.15,
                "Mar": 9826.72,
                "Apr": 9864.34,
                "May": 9912.53
            }
        }
      },
      {
        "AllCash": {
            "ytd": {
                "Jan": 66032.50,
                "Feb": 66063.26,
                "Mar": 66062.57,
                "Apr": 66062.22,
                "May": 66117.86
            }
        }
      }
    ],
    "Other": [
      {
        "source": "T.Rowe Price Institutional Lrg Cp Gr Fd",
        "amount": 21825.53,
        "history": {
            "ytd": {
                "Jan": 22145.45,
                "Feb": 22012.74,
                "Mar": 21978.65,
                "Apr": 21917.21,
                "May": 21825.53
            }
        }
      },
      {
        "source": "Fidelity Growth Discovery Fund",
        "amount": 6419.78,
        "history": {
            "ytd": {
                "Jan": 6917.52,
                "Feb": 6788.02,
                "Mar": 6646.22,
                "Apr": 6424.24,
                "May": 6419.78
            }
        }
      },
      {
        "AllOther": {
            "ytd": {
                "Jan": 29062.97,
                "Feb": 28800.76,
                "Mar": 28624.87,
                "Apr": 28341.45,
                "May": 28245.31
            }
        }
      }
    ]
  }
